{
  "team_player_data": {
    "year": 1972,
    "teams": {
      "Sydney": [
        {
          "firstname": "John",
          "lastname": "Rantall",
          "jumper": "5",
          "dob": "1943-12-09",
          "height": "182cm",
          "weight": "77kg"
        },
        {
          "firstname": "Peter",
          "lastname": "Bedford",
          "jumper": "11",
          "dob": "1947-04-11",
          "height": "180cm",
          "weight": "75kg"
        },
        {
          "firstname": "Reg",
          "lastname": "Gleeson",
          "jumper": "27",
          "dob": "1950-05-01",
          "height": "183cm",
          "weight": "79kg"
        },
        {
          "firstname": "Ricky",
          "lastname": "Quade",
          "jumper": "16",
          "dob": "1950-08-26",
          "height": "185cm",
          "weight": "88kg"
        },
        {
          "firstname": "Russell",
          "lastname": "Cook",
          "jumper": "17",
          "dob": "1947-09-23",
          "height": "185cm",
          "weight": "85kg"
        },
        {
          "firstname": "John",
          "lastname": "Pitura",
          "jumper": "21",
          "dob": "1950-09-21",
          "height": "185cm",
          "weight": "86kg"
        },
        {
          "firstname": "Jim",
          "lastname": "Prentice",
          "jumper": "19",
          "dob": "1949-12-28",
          "height": "187cm",
          "weight": "89kg"
        },
        {
          "firstname": "David",
          "lastname": "Mc Leish",
          "jumper": "29",
          "dob": "1950-02-21",
          "height": "180cm",
          "weight": "76kg"
        },
        {
          "firstname": "Norm",
          "lastname": "Goss Jnr",
          "jumper": "12",
          "dob": "1951-03-03",
          "height": "177cm",
          "weight": "78kg"
        },
        {
          "firstname": "Stephen",
          "lastname": "Officer",
          "jumper": "3",
          "dob": "1949-08-18",
          "height": "191cm",
          "weight": "83kg"
        },
        {
          "firstname": "Ray",
          "lastname": "Ball",
          "jumper": "31",
          "dob": "1949-02-20",
          "height": "185cm",
          "weight": "86kg"
        },
        {
          "firstname": "Peter",
          "lastname": "Brown",
          "jumper": "32",
          "dob": "1952-08-09",
          "height": "191cm",
          "weight": "86kg"
        },
        {
          "firstname": "Steve",
          "lastname": "Hoffman",
          "jumper": "26",
          "dob": "1951-09-21",
          "height": "169cm",
          "weight": "70kg"
        },
        {
          "firstname": "Shane",
          "lastname": "Mc Kew",
          "jumper": "35",
          "dob": "1949-03-01",
          "height": "184cm",
          "weight": "78kg"
        },
        {
          "firstname": "Lance",
          "lastname": "Morton",
          "jumper": "8",
          "dob": "1948-04-14",
          "height": "192cm",
          "weight": "96kg"
        },
        {
          "firstname": "Bruce",
          "lastname": "Davis",
          "jumper": "18",
          "dob": "1953-03-26",
          "height": "178cm",
          "weight": "88kg"
        },
        {
          "firstname": "Eric",
          "lastname": "Moore",
          "jumper": "22",
          "dob": "1948-04-29",
          "height": "183cm",
          "weight": "87kg"
        },
        {
          "firstname": "John",
          "lastname": "Murphy",
          "jumper": "6",
          "dob": "1945-01-12",
          "height": "183cm",
          "weight": "86kg"
        },
        {
          "firstname": "Neville",
          "lastname": "Miller",
          "jumper": "13",
          "dob": "1951-09-29",
          "height": "187cm",
          "weight": "86kg"
        },
        {
          "firstname": "Robert",
          "lastname": "Doyle",
          "jumper": "28",
          "dob": "1951-01-14",
          "height": "196cm",
          "weight": "97kg"
        },
        {
          "firstname": "Jim",
          "lastname": "Haines",
          "jumper": "1",
          "dob": "1945-12-20",
          "height": "185cm",
          "weight": "81kg"
        },
        {
          "firstname": "Jim",
          "lastname": "Wilkinson",
          "jumper": "9",
          "dob": "1951-12-04",
          "height": "182cm",
          "weight": "76kg"
        },
        {
          "firstname": "Bob",
          "lastname": "Bell",
          "jumper": "24",
          "dob": "1953-06-22",
          "height": "191cm",
          "weight": "88kg"
        },
        {
          "firstname": "Russell",
          "lastname": "Mc Henry",
          "jumper": "36",
          "dob": "1950-04-21",
          "height": "170cm",
          "weight": "72kg"
        },
        {
          "firstname": "Wayne",
          "lastname": "Walsh",
          "jumper": "10",
          "dob": "1946-05-07",
          "height": "178cm",
          "weight": "76kg"
        },
        {
          "firstname": "Max",
          "lastname": "Robertson",
          "jumper": "23",
          "dob": "1954-09-14",
          "height": "185cm",
          "weight": "87kg"
        },
        {
          "firstname": "Wayne",
          "lastname": "Ewin",
          "jumper": "43",
          "dob": "1953-12-04",
          "height": "175cm",
          "weight": "67kg"
        },
        {
          "firstname": "Robert",
          "lastname": "Hay",
          "jumper": "2",
          "dob": "1954-09-21",
          "height": "183cm",
          "weight": "84kg"
        },
        {
          "firstname": "Gary",
          "lastname": "Brice",
          "jumper": "7",
          "dob": "1948-10-07",
          "height": "180cm",
          "weight": "78kg"
        },
        {
          "firstname": "Keith",
          "lastname": "Baskin",
          "jumper": "4",
          "dob": "1945-12-15",
          "height": "183cm",
          "weight": "80kg"
        },
        {
          "firstname": "George",
          "lastname": "Lakes",
          "jumper": "9",
          "dob": "1949-08-23",
          "height": "185cm",
          "weight": "82kg"
        },
        {
          "firstname": "Brian",
          "lastname": "Woodman",
          "jumper": "50",
          "dob": "1950-10-10",
          "height": "175cm",
          "weight": "70kg"
        },
        {
          "firstname": "Stewart",
          "lastname": "Gull",
          "jumper": "34",
          "dob": "1951-06-24",
          "height": "191cm",
          "weight": "87kg"
        },
        {
          "firstname": "Garry",
          "lastname": "Robertson",
          "jumper": "15",
          "dob": "1953-03-02",
          "height": "184cm",
          "weight": "77kg"
        },
        {
          "firstname": "Greg",
          "lastname": "Miller",
          "jumper": "48",
          "dob": "1953-05-08",
          "height": "188cm",
          "weight": "88kg"
        },
        {
          "firstname": "Mick",
          "lastname": "Plant",
          "jumper": "49",
          "dob": "1953-06-01",
          "height": "177cm",
          "weight": "76kg"
        },
        {
          "firstname": "Greg",
          "lastname": "Lambert",
          "jumper": "33",
          "dob": "1947-03-01",
          "height": "178cm",
          "weight": "76kg"
        },
        {
          "firstname": "Michael",
          "lastname": "Norris",
          "jumper": "39",
          "dob": "1954-10-06",
          "height": "171cm",
          "weight": "66kg"
        },
        {
          "firstname": "Graham",
          "lastname": "Dempster",
          "jumper": "45",
          "dob": "1955-01-14",
          "height": "192cm",
          "weight": "83kg"
        },
        {
          "firstname": "Robert",
          "lastname": "Stibbard",
          "jumper": "42",
          "dob": "1952-02-09",
          "height": "180cm",
          "weight": "80kg"
        },
        {
          "firstname": "Robert",
          "lastname": "Grima",
          "jumper": "30",
          "dob": "1952-01-26",
          "height": "187cm",
          "weight": "85kg"
        },
        {
          "firstname": "Trevor",
          "lastname": "Carrodus",
          "jumper": "38",
          "dob": "1952-11-29",
          "height": "188cm",
          "weight": "82kg"
        },
        {
          "firstname": "Peter",
          "lastname": "Kerr",
          "jumper": "45",
          "dob": "1954-03-26",
          "height": "180cm",
          "weight": "83kg"
        },
        {
          "firstname": "Haydn",
          "lastname": "Mc Auliffe",
          "jumper": "25",
          "dob": "1946-05-15",
          "height": "175cm",
          "weight": "76kg"
        },
        {
          "firstname": "Peter",
          "lastname": "Mc Cracken",
          "jumper": "22",
          "dob": "1949-12-01",
          "height": "175cm",
          "weight": "76kg"
        }
      ]
    }
  }
}