{
  "team_player_data": {
    "year": 1917,
    "teams": {
      "Sydney": [
        {
          "firstname": "Bill",
          "lastname": "Daly",
          "jumper": "9",
          "dob": "1892-11-07",
          "height": "—",
          "weight": "—"
        },
        {
          "firstname": "Arthur",
          "lastname": "Rademacher",
          "jumper": "9",
          "dob": "1889-11-27",
          "height": "175cm",
          "weight": "76kg"
        },
        {
          "firstname": "Bob",
          "lastname": "Deas",
          "jumper": "8",
          "dob": "1886-09-17",
          "height": "180cm",
          "weight": "82kg"
        },
        {
          "firstname": "Vic",
          "lastname": "Belcher",
          "jumper": "2",
          "dob": "1888-08-24",
          "height": "180cm",
          "weight": "80kg"
        },
        {
          "firstname": "Harold",
          "lastname": "Robertson",
          "jumper": "29",
          "dob": "1895-04-09",
          "height": "173cm",
          "weight": "67kg"
        },
        {
          "firstname": "Harry",
          "lastname": "Morgan",
          "jumper": "18",
          "dob": "1889-03-24",
          "height": "180cm",
          "weight": "73kg"
        },
        {
          "firstname": "Jack",
          "lastname": "Howell Snr",
          "jumper": "14",
          "dob": "1895-03-16",
          "height": "—",
          "weight": "—"
        },
        {
          "firstname": "Mark",
          "lastname": "Tandy",
          "jumper": "27",
          "dob": "1892-09-03",
          "height": "173cm",
          "weight": "70kg"
        },
        {
          "firstname": "Jim",
          "lastname": "Caldwell",
          "jumper": "2",
          "dob": "1888-08-11",
          "height": "173cm",
          "weight": "66kg"
        },
        {
          "firstname": "Jack",
          "lastname": "Brennan",
          "jumper": "2",
          "dob": "1897-08-18",
          "height": "—",
          "weight": "—"
        },
        {
          "firstname": "Alf",
          "lastname": "Boyce",
          "jumper": "10",
          "dob": "1895-03-03",
          "height": "178cm",
          "weight": "70kg"
        },
        {
          "firstname": "Ben",
          "lastname": "Hair",
          "jumper": "25",
          "dob": "1892-09-29",
          "height": "178cm",
          "weight": "79kg"
        },
        {
          "firstname": "Dick",
          "lastname": "Hutchinson",
          "jumper": "4",
          "dob": "1890-02-17",
          "height": "—",
          "weight": "—"
        },
        {
          "firstname": "Jock",
          "lastname": "Doherty",
          "jumper": "6",
          "dob": "1894-10-03",
          "height": "—",
          "weight": "—"
        },
        {
          "firstname": "Artie",
          "lastname": "Wood",
          "jumper": "17",
          "dob": "1898-06-24",
          "height": "163cm",
          "weight": "62kg"
        },
        {
          "firstname": "Joe",
          "lastname": "Prince",
          "jumper": "19",
          "dob": "1885-09-30",
          "height": "164cm",
          "weight": "62kg"
        },
        {
          "firstname": "Dick",
          "lastname": "Mullaly",
          "jumper": "17",
          "dob": "1892-06-19",
          "height": "178cm",
          "weight": "71kg"
        },
        {
          "firstname": "Gerald",
          "lastname": "Ryan",
          "jumper": "27",
          "dob": "1895-12-27",
          "height": "180cm",
          "weight": "72kg"
        },
        {
          "firstname": "Phil",
          "lastname": "Skehan",
          "jumper": "26",
          "dob": "1894-06-21",
          "height": "—",
          "weight": "—"
        },
        {
          "firstname": "George",
          "lastname": "Payne",
          "jumper": "15",
          "dob": "1893-11-28",
          "height": "185cm",
          "weight": "81kg"
        },
        {
          "firstname": "Harry",
          "lastname": "Purdy Jnr",
          "jumper": "21",
          "dob": "1898-03-18",
          "height": "168cm",
          "weight": "62kg"
        },
        {
          "firstname": "Tom",
          "lastname": "Bollard",
          "jumper": "23",
          "dob": "1890-10-16",
          "height": "173cm",
          "weight": "66kg"
        },
        {
          "firstname": "Alan",
          "lastname": "O' Donoghue",
          "jumper": "13",
          "dob": "1891-06-03",
          "height": "183cm",
          "weight": "78kg"
        },
        {
          "firstname": "Mal",
          "lastname": "Lowrie",
          "jumper": "26",
          "dob": "1898-03-10",
          "height": "177cm",
          "weight": "73kg"
        },
        {
          "firstname": "Jim",
          "lastname": "Ashton",
          "jumper": "7",
          "dob": "1891-04-12",
          "height": "—",
          "weight": "—"
        },
        {
          "firstname": "Jim",
          "lastname": "Stewart",
          "jumper": "25",
          "dob": "1889-08-13",
          "height": "—",
          "weight": "—"
        },
        {
          "firstname": "Sydney",
          "lastname": "Strong",
          "jumper": "23",
          "dob": "1897-10-09",
          "height": "—",
          "weight": "—"
        },
        {
          "firstname": "Wal",
          "lastname": "Jenkins",
          "jumper": "22",
          "dob": "1897-01-09",
          "height": "—",
          "weight": "—"
        },
        {
          "firstname": "George",
          "lastname": "Moloney",
          "jumper": "16",
          "dob": "1894-10-19",
          "height": "—",
          "weight": "—"
        },
        {
          "firstname": "Harry",
          "lastname": "Lakin",
          "jumper": "31",
          "dob": "1897-01-30",
          "height": "—",
          "weight": "—"
        }
      ]
    }
  }
}