{
  "team_player_data": {
    "year": 1985,
    "teams": {
      "Essendon": [
        {
          "firstname": "Tim",
          "lastname": "Watson",
          "jumper": "32",
          "dob": "1961-07-13",
          "height": "185cm",
          "weight": "96kg"
        },
        {
          "firstname": "Mark",
          "lastname": "Harvey",
          "jumper": "38",
          "dob": "1965-06-11",
          "height": "184cm",
          "weight": "87kg"
        },
        {
          "firstname": "Paul",
          "lastname": "Weston",
          "jumper": "28",
          "dob": "1957-04-09",
          "height": "188cm",
          "weight": "85kg"
        },
        {
          "firstname": "Garry",
          "lastname": "Foulds",
          "jumper": "10",
          "dob": "1956-05-13",
          "height": "188cm",
          "weight": "78kg"
        },
        {
          "firstname": "Leon",
          "lastname": "Baker",
          "jumper": "4",
          "dob": "1956-08-17",
          "height": "183cm",
          "weight": "85kg"
        },
        {
          "firstname": "Mark",
          "lastname": "Thompson",
          "jumper": "26",
          "dob": "1963-11-19",
          "height": "177cm",
          "weight": "87kg"
        },
        {
          "firstname": "Roger",
          "lastname": "Merrett",
          "jumper": "25",
          "dob": "1960-04-19",
          "height": "195cm",
          "weight": "99kg"
        },
        {
          "firstname": "Tony",
          "lastname": "Elshaug",
          "jumper": "14",
          "dob": "1960-07-19",
          "height": "178cm",
          "weight": "73kg"
        },
        {
          "firstname": "Paul",
          "lastname": "VanDerHaar",
          "jumper": "18",
          "dob": "1958-03-07",
          "height": "192cm",
          "weight": "93kg"
        },
        {
          "firstname": "Frank",
          "lastname": "Dunell",
          "jumper": "7",
          "dob": "1958-03-17",
          "height": "185cm",
          "weight": "85kg"
        },
        {
          "firstname": "Darren",
          "lastname": "Williams",
          "jumper": "13",
          "dob": "1960-10-13",
          "height": "176cm",
          "weight": "76kg"
        },
        {
          "firstname": "Simon",
          "lastname": "Madden",
          "jumper": "27",
          "dob": "1957-12-30",
          "height": "198cm",
          "weight": "99kg"
        },
        {
          "firstname": "Kevin",
          "lastname": "Walsh",
          "jumper": "30",
          "dob": "1962-02-09",
          "height": "193cm",
          "weight": "82kg"
        },
        {
          "firstname": "Glenn",
          "lastname": "Hawker",
          "jumper": "33",
          "dob": "1961-03-17",
          "height": "185cm",
          "weight": "84kg"
        },
        {
          "firstname": "Alan",
          "lastname": "Ezard",
          "jumper": "15",
          "dob": "1963-04-15",
          "height": "173cm",
          "weight": "68kg"
        },
        {
          "firstname": "Terry",
          "lastname": "Daniher",
          "jumper": "5",
          "dob": "1957-08-15",
          "height": "188cm",
          "weight": "89kg"
        },
        {
          "firstname": "Stephen",
          "lastname": "Carey",
          "jumper": "17",
          "dob": "1959-10-14",
          "height": "180cm",
          "weight": "89kg"
        },
        {
          "firstname": "Bryan",
          "lastname": "Wood",
          "jumper": "2",
          "dob": "1954-04-03",
          "height": "185cm",
          "weight": "85kg"
        },
        {
          "firstname": "Merv",
          "lastname": "Neagle",
          "jumper": "1",
          "dob": "1958-03-07",
          "height": "181cm",
          "weight": "79kg"
        },
        {
          "firstname": "Neil",
          "lastname": "Clarke",
          "jumper": "8",
          "dob": "1957-08-28",
          "height": "177cm",
          "weight": "80kg"
        },
        {
          "firstname": "Peter",
          "lastname": "Bradbury",
          "jumper": "36",
          "dob": "1958-07-02",
          "height": "183cm",
          "weight": "84kg"
        },
        {
          "firstname": "Rene",
          "lastname": "Kink",
          "jumper": "23",
          "dob": "1956-11-22",
          "height": "183cm",
          "weight": "91kg"
        },
        {
          "firstname": "Shane",
          "lastname": "Heard",
          "jumper": "9",
          "dob": "1958-07-28",
          "height": "177cm",
          "weight": "79kg"
        },
        {
          "firstname": "Chris",
          "lastname": "Waterson",
          "jumper": "35",
          "dob": "1961-03-26",
          "height": "183cm",
          "weight": "76kg"
        },
        {
          "firstname": "Bill",
          "lastname": "Duckworth",
          "jumper": "22",
          "dob": "1959-02-21",
          "height": "187cm",
          "weight": "85kg"
        },
        {
          "firstname": "Michael",
          "lastname": "Thomson",
          "jumper": "34",
          "dob": "1961-11-26",
          "height": "187cm",
          "weight": "86kg"
        },
        {
          "firstname": "Peter",
          "lastname": "Banfield",
          "jumper": "16",
          "dob": "1965-01-21",
          "height": "177cm",
          "weight": "80kg"
        },
        {
          "firstname": "Neale",
          "lastname": "Daniher",
          "jumper": "6",
          "dob": "1961-02-15",
          "height": "188cm",
          "weight": "84kg"
        },
        {
          "firstname": "Paul",
          "lastname": "Salmon",
          "jumper": "3",
          "dob": "1965-01-20",
          "height": "205cm",
          "weight": "112kg"
        },
        {
          "firstname": "Steven",
          "lastname": "Clark",
          "jumper": "12",
          "dob": "1961-05-15",
          "height": "173cm",
          "weight": "76kg"
        },
        {
          "firstname": "Trevor",
          "lastname": "Spencer",
          "jumper": "23",
          "dob": "1965-06-28",
          "height": "190cm",
          "weight": "89kg"
        },
        {
          "firstname": "Brian",
          "lastname": "Winton",
          "jumper": "24",
          "dob": "1963-07-28",
          "height": "192cm",
          "weight": "83kg"
        },
        {
          "firstname": "Stephen",
          "lastname": "Pirrie",
          "jumper": "29",
          "dob": "1961-03-23",
          "height": "191cm",
          "weight": "92kg"
        },
        {
          "firstname": "Merv",
          "lastname": "Harbinson",
          "jumper": "37",
          "dob": "1959-06-11",
          "height": "180cm",
          "weight": "83kg"
        }
      ]
    }
  }
}